<?xml version="1.0" encoding="UTF-8"?>
<Model>
  <DataType name="BaseExampleCategory" parent="CommonEntity" meta="x:13;y:10;child:ExampleCategory" matchType="com.bstek.dorado.sample.entity.ExampleCategory">
    <PropertyDef name="label" label="标题" required="true"/>
    <PropertyDef name="icon" label="图标"/>
  </DataType>
  <DataType name="ExampleCategory" parent="BaseExampleCategory" meta="x:8;y:164" autoCreatePropertyDefs="true">
    <PropertyDef name="new" label="是否新示例"/>
    <PropertyDef name="hot" label="是否重点示例"/>
    <PropertyDef name="url" label="路径"/>
    <PropertyDef name="tags" label="标签"/>
    <PropertyDef name="summary" label="说明"/>
  </DataType>
  <DataType name="BaseExample" parent="CommonEntity" meta="x:176;y:10;child:Example" matchType="com.bstek.dorado.sample.entity.Example">
    <PropertyDef name="label" label="标题" required="true"/>
    <PropertyDef name="icon" label="图标"/>
  </DataType>
  <DataType name="Example" parent="BaseExample" meta="x:181;y:164" autoCreatePropertyDefs="true">
    <PropertyDef name="author" label="作者"/>
    <PropertyDef name="createDate" defaultValue="${util.getDate()}" label="创建日期"/>
    <PropertyDef name="lastModify" defaultValue="${util.getDate()}" label="修改日期"/>
    <PropertyDef name="new" label="是否新示例"/>
    <PropertyDef name="hot" label="是否重点示例"/>
    <PropertyDef name="embedded">
      <Property name="label">是否嵌入模式</Property>
    </PropertyDef>
    <PropertyDef name="embedWidth">
      <Property name="label">嵌入模式宽度</Property>
    </PropertyDef>
    <PropertyDef name="embedHeight">
      <Property name="label">嵌入模式高度</Property>
    </PropertyDef>
    <PropertyDef name="url" label="路径"/>
    <PropertyDef name="tags" label="标签"/>
    <PropertyDef name="summary" label="说明"/>
  </DataType>
  <DataType name="ExampleSource" parent="CommonEntity" meta="x:319;y:10" autoCreatePropertyDefs="true" matchType="com.bstek.dorado.sample.entity.ExampleSource">
    <PropertyDef name="label" label="标题" required="true"/>
    <PropertyDef name="path" label="路径" required="true"/>
    <PropertyDef name="summary" label="说明"/>
  </DataType>
</Model>
