<?xml version="1.0" encoding="UTF-8"?>
<ViewConfig>
  <Model>
    <DataType name="Employee" parent="global:Employee">
      <Reference name="underlings" dataProvider="employeeInterceptor#getEmployeesBySuperior" dataType="[SELF]" parameter="$${this.id}"/>
    </DataType>
  </Model>
  <View title="Employee Maintain">
    <DataSet id="dsEmployees" dataProvider="employeeInterceptor#getEmployeesBySuperior" dataType="[Employee]"/>
    <UpdateAction id="actionSave" caption="Save" dataResolver="employeeInterceptor#saveAll" icon="url(>skin>common/icons.gif) -140px -20px">
      <Property name="successMessage">OK.</Property>
      <UpdateItem dataPath="underlings[#dirty](R)" dataSet="dsEmployees"/>
    </UpdateAction>
    <ToolBar layoutConstraint="top">
      <DataPilot dataSet="dsEmployees" itemCodes="pages,|,+,-,x"/>
      <Separator/>
      <ToolBarButton action="actionSave"/>
    </ToolBar>
    <DataTreeGrid dataSet="dsEmployees" treeColumn="firstName">
      <Property name="dynaRowHeight">true</Property>
      <Property name="draggable">true</Property>
      <Property name="droppable">true</Property>
      <Property name="dropMode">onOrInsertItems</Property>
      <Property name="dragTags">employee</Property>
      <Property name="droppableTags">employee</Property>
      <BindingConfigs>
        <BindingConfig childrenProperty="underlings" expandLevel="3" labelProperty="firstName" recursive="true"/>
      </BindingConfigs>
      <Columns>
        <IndicatorColumn/>
        <DataColumn property="firstName" width="160"/>
        <DataColumn property="lastName"/>
        <DataColumn property="sex"/>
        <DataColumn property="titleOfCourtesy"/>
        <DataColumn property="birthDate"/>
        <DataColumn property="city"/>
      </Columns>
    </DataTreeGrid>
  </View>
</ViewConfig>
